machaao/__init__.py
machaao/chatbot.py
machaao/machaao.py
machaao/machaaoapi.py
machaao/main.py
machaao/mhttp.py
machaao/mxtunnel.py
machaao-0.3.5.dist-info/LICENSE
machaao-0.3.5.dist-info/METADATA
machaao-0.3.5.dist-info/WHEEL
machaao-0.3.5.dist-info/entry_points.txt
machaao-0.3.5.dist-info/top_level.txt
machaao-0.3.5.dist-info/RECORD
