Metadata-Version: 2.1
Name: machaao
Version: 0.3.5
Summary: A module for python developers looking to build, prototype & deploy deeply personalized chatbots
Home-page: https://github.com/machaao/machaao-py
Author: Abhishek Raj
Author-email: abhishek@machaao.com
License: UNKNOWN
Platform: UNKNOWN
Classifier: Programming Language :: Python :: 3
Classifier: License :: OSI Approved :: MIT License
Classifier: Operating System :: OS Independent
Requires-Python: >=3.6
License-File: LICENSE
Requires-Dist: requests
Requires-Dist: pyjwt
Requires-Dist: asyncio
Requires-Dist: flask
Requires-Dist: httpx
Requires-Dist: bs4
Requires-Dist: Flask-API
Requires-Dist: click
Requires-Dist: certifi
Requires-Dist: websockets
Requires-Dist: aiohttp
